bbta-0.3.2.dist-info/RECORD
bbta-0.3.2.dist-info/WHEEL
bbta-0.3.2.dist-info/top_level.txt
bbta-0.3.2.dist-info/METADATA
bbta-0.3.2.dist-info/licenses/LICENSE
bbta/build.py
bbta/bbta.go
bbta/_bbta.cpython-311-darwin.h
bbta/_bbta.cpython-311-darwin.so
bbta/tav.py
bbta/__init__.py
bbta/bbta_go.h
bbta/bbta.c
bbta/go.py
bbta/ta.py
