Metadata-Version: 2.1
Name: bbta
Version: 0.3.2
Summary: python bindings for banta
Home-page: https://github.com/banbox/banta
Author: banbot
Author-email: banbot@163.com
Classifier: Programming Language :: Python :: 3
Classifier: License :: OSI Approved :: BSD License
Classifier: Operating System :: OS Independent
License-File: LICENSE
